gear/__init__.py
gear/cli.py
gear/log.py
gear/multi_app.py
gear/o.py
gear/rpc.py
gear/testclient.py
gear/meter/__init__.py
gear/meter/account.py
gear/meter/client.py
gear/meter/request.py
gear/utils/__init__.py
gear/utils/compat.py
gear/utils/keystore.py
gear/utils/singleton.py
gear/utils/thread.py
gear/utils/types.py
meter_gear-1.2.92.dist-info/LICENSE
meter_gear-1.2.92.dist-info/METADATA
meter_gear-1.2.92.dist-info/WHEEL
meter_gear-1.2.92.dist-info/entry_points.txt
meter_gear-1.2.92.dist-info/top_level.txt
meter_gear-1.2.92.dist-info/RECORD
