Metadata-Version: 2.1
Name: meter-gear
Version: 1.2.92
Summary: An adapter between meter-restful and eth-rpc.
Home-page: https://github.com/meterio/meter-gear
Author: Simon Zhang
Author-email: zhanghan.simon@gmail.com
License: MIT
Keywords: meter blockchain ethereum
Classifier: Intended Audience :: Developers
Classifier: Programming Language :: Python :: 3.9
Requires-Python: >=3.9
License-File: LICENSE
Requires-Dist: pbkdf2
Requires-Dist: pycryptodome
Requires-Dist: scrypt
Requires-Dist: werkzeug
Requires-Dist: requests
Requires-Dist: aiohttp
Requires-Dist: jsonrpcserver ==5.0.7
Requires-Dist: lru-dict
Requires-Dist: eth-keys
Requires-Dist: eth-utils ==2.0.0
Requires-Dist: click
Requires-Dist: rlp ==4.0.0
Requires-Dist: websockets ==10.1
Requires-Dist: eth-abi ==5.0.0
